nonebot_plugin_arkrecord/__init__.py
nonebot_plugin_arkrecord/ark/__init__.py
nonebot_plugin_arkrecord/ark/ark_db.py
nonebot_plugin_arkrecord/ark/ark_drawer.py
nonebot_plugin_arkrecord/ark/ark_import.py
nonebot_plugin_arkrecord/ark/ark_operator.py
nonebot_plugin_arkrecord/ark/ark_record.py
nonebot_plugin_arkrecord/ark/ark_scrawl.py
nonebot_plugin_arkrecord/ark/ark_setting.py
nonebot_plugin_arkrecord/ark/ark_style.py
nonebot_plugin_arkrecord/ark/ark_update.py
nonebot_plugin_arkrecord/ark/ark_utils.py
nonebot_plugin_arkrecord/res_file/output_csv/ark_record_812325695_白银御行的直升机#4133.xlsx
nonebot_plugin_arkrecord/res_file/record_image/record_img_10850607.png
nonebot_plugin_arkrecord/res_file/record_image/record_img_1394586.png
nonebot_plugin_arkrecord/res_file/record_image/record_img_244092727.png
nonebot_plugin_arkrecord/res_file/record_image/record_img_59234008.png
nonebot_plugin_arkrecord/res_file/record_image/record_img_594209837.png
nonebot_plugin_arkrecord/res_file/record_image/record_img_62572.png
nonebot_plugin_arkrecord/res_file/record_image/record_img_70036345.png
nonebot_plugin_arkrecord/res_file/record_image/record_img_746282064.png
nonebot_plugin_arkrecord/res_file/record_image/record_img_748910231.png
nonebot_plugin_arkrecord/res_file/record_image/record_img_78759166.png
nonebot_plugin_arkrecord/res_file/record_image/record_img_85084083.png
nonebot_plugin_arkrecord/res_file/record_image/record_img_870599048.png
nonebot_plugin_arkrecord/res_file/record_image/record_img_914376505.png
nonebot_plugin_arkrecord/resource/arkgacha_record16 copy.db
nonebot_plugin_arkrecord/resource/arkgacha_record16.db
nonebot_plugin_arkrecord/resource/arkgacha_record_deprecated.db
nonebot_plugin_arkrecord/resource/images/ark_help.png
nonebot_plugin_arkrecord/resource/images/ark_helpold.png
nonebot_plugin_arkrecord/resource/images/bottom.png
nonebot_plugin_arkrecord/resource/images/rainbow.png
nonebot_plugin_arkrecord/resource/images/titleimage.png
nonebot_plugin_arkrecord-1.7.1.dist-info/WHEEL
nonebot_plugin_arkrecord-1.7.1.dist-info/METADATA
nonebot_plugin_arkrecord-1.7.1.dist-info/RECORD
