Metadata-Version: 2.1
Name: nonebot-plugin-arkrecord
Version: 1.7.1
Summary: Nonebot plugin for fetching and analyzing gacha records of arknights
Home-page: https://github.com/zheuziihau
License: MIT
Keywords: gacha,arknights,nonebot
Author: kwtk
Requires-Python: >=3.8,<4.0
Classifier: Development Status :: 4 - Beta
Classifier: Environment :: Web Environment
Classifier: Framework :: AsyncIO
Classifier: Intended Audience :: Developers
Classifier: License :: OSI Approved :: MIT License
Classifier: Operating System :: POSIX
Classifier: Programming Language :: Python
Classifier: Programming Language :: Python :: 3
Classifier: Programming Language :: Python :: 3.8
Classifier: Programming Language :: Python :: 3.9
Classifier: Programming Language :: Python :: 3.10
Classifier: Programming Language :: Python :: 3
Classifier: Programming Language :: Python :: 3 :: Only
Classifier: Programming Language :: Python :: 3.8
Classifier: Topic :: Software Development
Classifier: Topic :: Software Development :: Libraries
Requires-Dist: BeautifulSoup4
Requires-Dist: Pillow
Requires-Dist: XlsxWriter
Requires-Dist: lxml
Requires-Dist: matplotlib
Requires-Dist: nonebot-adapter-onebot (>=2.0.0b1,<3.0.0)
Requires-Dist: nonebot2 (>=2.0.0b4,<3.0.0)
Requires-Dist: requests
Project-URL: Repository, https://github.com/zheuziihau/nonebot_plugin_arkrecord
